mpunittest/__init__.py
mpunittest/comm.py
mpunittest/logging.py
mpunittest/result.py
mpunittest/run.py
mpunittest/runner.py
mpunittest/streamctx.py
mpunittest/html/__init__.py
mpunittest/html/result.html
mpunittest/tests/__init__.py
mpunittest/tests/dummy/__init__.py
mpunittest/tests/dummy/dirs/__init__.py
mpunittest/tests/dummy/dirs/dir1/__init__.py
mpunittest/tests/dummy/dirs/dir1/dummytest.py
mpunittest/tests/dummy/dirs/dir2/__init__.py
mpunittest/tests/dummy/dirs/dir2/dummytest.py
mpunittest/tests/dummy/dirs/dir3/__init__.py
mpunittest/tests/dummy/dirs/dir3/dummytest.py
mpunittest/tests/real/__init__.py
mpunittest/tests/real/manual.py
mpunittest/tests/real/testcomm.py
mpunittest/tests/real/testrunner.py
mpunittest-0.0.0a6.dist-info/METADATA
mpunittest-0.0.0a6.dist-info/WHEEL
mpunittest-0.0.0a6.dist-info/licenses/COPYING
mpunittest-0.0.0a6.dist-info/RECORD
