Metadata-Version: 2.1
Name: mpunittest
Version: 0.0.0a6
Summary: Multi core processing of unittests
Project-URL: repository, https://github.com/maximilianpilz/mpunittest.git
Author: Maximilian Pilz
Author-email: maximilian.pilz.git@gmail.com
Maintainer-email: Maximilian Pilz <maximilian.pilz.git@gmail.com>
License: GPL-2.0-only
License-File: COPYING
Keywords: multiprocessing,parallel,process,processes,runner,unittest,unittests
Classifier: Development Status :: 3 - Alpha
Classifier: Intended Audience :: Developers
Classifier: License :: OSI Approved :: GNU General Public License v2 (GPLv2)
Classifier: Programming Language :: Python :: 3
Classifier: Programming Language :: Python :: 3 :: Only
Classifier: Programming Language :: Python :: 3.8
Classifier: Programming Language :: Python :: 3.9
Classifier: Programming Language :: Python :: 3.10
Classifier: Programming Language :: Python :: 3.11
Classifier: Programming Language :: Python :: Implementation :: CPython
Classifier: Topic :: Software Development :: Testing
Classifier: Topic :: Software Development :: Testing :: Unit
Requires-Python: >=3.8
